README
setup.cfg
setup.py
GenerateRoman/GenerateRoman.py
GenerateRoman/__init__.py
GenerateRoman.egg-info/PKG-INFO
GenerateRoman.egg-info/SOURCES.txt
GenerateRoman.egg-info/dependency_links.txt
GenerateRoman.egg-info/top_level.txt