Metadata-Version: 1.1
Name: GenerateRoman
Version: 0.4
Summary: Generate Roman no from an integer
Home-page: https://github.com/shubham039/GetRoman
Author: Shubham Ringne
Author-email: shubhamringne@gmail.com
License: UNKNOWN
Download-URL: https://github.com/shubham039/GetRoman/archive/0.4.tar.gz
Keywords: roman,convert,integer to roman
Platform: UNKNOWN
